{
  "userBanned": [
    [
      "@JORDAN",
      true
    ],
    [
      "Ava",
      true
    ],
    [
      "100012191281263",
      true
    ],
    [
      "100088729275370",
      true
    ],
    [
      "61573096023161",
      true
    ],
    [
      "61563047813798",
      true
    ],
    [
      "100095303266512",
      true
    ],
    [
      "100072423856167",
      true
    ]
  ],
  "banDetails": [
    [
      "@JORDAN",
      {
        "name": "Facebook users",
        "uid": "@JORDAN",
        "reason": ". Ye Meri Gand Ka BoLTa Hai MoTi HoJay Gi HeeRa BeTy 👈🏻💋",
        "timestamp": "2025-07-05 23:41:27",
        "bannedBy": "Facebook users"
      }
    ],
    [
      "Ava",
      {
        "name": "Facebook users",
        "uid": "Ava",
        "reason": "BoTni: 100088729275370 Botni Thi SaLi",
        "timestamp": "2025-07-05 23:44:56",
        "bannedBy": "Facebook users"
      }
    ],
    [
      "100012191281263",
      {
        "name": "Facebook users",
        "uid": "100012191281263",
        "reason": "Auto-ban: Spam detected",
        "timestamp": "2025-07-05 23:45:18",
        "bannedBy": "SYSTEM"
      }
    ],
    [
      "100088729275370",
      {
        "name": "Facebook users",
        "uid": "100088729275370",
        "reason": "BoT Ha",
        "timestamp": "2025-07-06 00:10:51",
        "bannedBy": "Facebook users"
      }
    ],
    [
      "61573096023161",
      {
        "name": "Facebook users",
        "uid": "61573096023161",
        "reason": "Auto-ban: Spam detected",
        "timestamp": "2025-07-06 04:51:08",
        "bannedBy": "SYSTEM"
      }
    ],
    [
      "61563047813798",
      {
        "name": "Facebook users",
        "uid": "61563047813798",
        "reason": "Auto-ban: Spam detected",
        "timestamp": "2025-07-06 07:16:50",
        "bannedBy": "SYSTEM"
      }
    ],
    [
      "100095303266512",
      {
        "name": "Facebook users",
        "uid": "100095303266512",
        "reason": "Auto-ban: Spam detected",
        "timestamp": "2025-07-06 08:11:48",
        "bannedBy": "SYSTEM"
      }
    ],
    [
      "100072423856167",
      {
        "name": "Facebook users",
        "uid": "100072423856167",
        "reason": "Auto-ban: Spam detected",
        "timestamp": "2025-07-06 08:14:30",
        "bannedBy": "SYSTEM"
      }
    ]
  ]
}